context_reference_store-1.0.18.dist-info/licenses/LICENSE
context_store/__init__.py
context_store/py.typed
context_store/adapters/__init__.py
context_store/adapters/composio_adapter.py
context_store/adapters/langchain_adapter.py
context_store/adapters/langgraph_adapter.py
context_store/adapters/llamaindex_adapter.py
context_store/core/__init__.py
context_store/core/async_context_store.py
context_store/core/base_state.py
context_store/core/compression_manager.py
context_store/core/context_reference_store.py
context_store/core/large_context_state.py
context_store/monitoring/__init__.py
context_store/monitoring/tui_dashboard.py
context_store/optimization/__init__.py
context_store/optimization/token_manager.py
context_store/semantic/__init__.py
context_store/semantic/semantic_analyzer.py
context_store/utils/__init__.py
context_store/utils/file_metrics_adapter.py
context_reference_store-1.0.18.dist-info/METADATA
context_reference_store-1.0.18.dist-info/WHEEL
context_reference_store-1.0.18.dist-info/top_level.txt
context_reference_store-1.0.18.dist-info/RECORD
