Metadata-Version: 2.4
Name: context-reference-store
Version: 1.0.18
Summary: Efficient Large Context Window Management for AI Agents and Frameworks
Author-email: Adewale Adenle <waleadenle1@gmail.com>
Maintainer-email: Adewale Adenle <waleadenle1@gmail.com>
License: Apache-2.0
Project-URL: Homepage, https://github.com/Adewale-1/Context_reference_store
Project-URL: Documentation, https://context-reference-store.readthedocs.io/
Project-URL: Repository, https://github.com/Adewale-1/Context_reference_store.git
Project-URL: Issues, https://github.com/Adewale-1/Context_reference_store/issues
Project-URL: Changelog, https://github.com/Adewale-1/Context_reference_store/blob/main/CHANGELOG.md
Keywords: ai,agents,context,memory,multimodal,adk,langchain,langgraph,llamaindex,composio,performance
Classifier: Development Status :: 4 - Beta
Classifier: Intended Audience :: Developers
Classifier: License :: OSI Approved :: Apache Software License
Classifier: Operating System :: OS Independent
Classifier: Programming Language :: Python :: 3
Classifier: Programming Language :: Python :: 3.10
Classifier: Programming Language :: Python :: 3.11
Classifier: Programming Language :: Python :: 3.12
Classifier: Topic :: Scientific/Engineering :: Artificial Intelligence
Classifier: Topic :: Software Development :: Libraries :: Python Modules
Requires-Python: >=3.10
License-File: LICENSE
Requires-Dist: psutil>=5.8.0
Requires-Dist: typing-extensions>=4.0.0; python_version < "3.10"
Requires-Dist: lz4>=4.0.0
Requires-Dist: aiofiles>=23.0.0
Requires-Dist: asyncio-throttle>=1.0.0
Provides-Extra: adk
Requires-Dist: adk-python>=0.1.0; extra == "adk"
Requires-Dist: asyncio-throttle>=1.0.0; extra == "adk"
Provides-Extra: langchain
Requires-Dist: langchain>=0.1.0; extra == "langchain"
Requires-Dist: langchain-core>=0.1.0; extra == "langchain"
Provides-Extra: langgraph
Requires-Dist: langgraph>=0.1.0; extra == "langgraph"
Provides-Extra: llamaindex
Requires-Dist: llama-index>=0.9.0; extra == "llamaindex"
Provides-Extra: composio
Requires-Dist: composio-core>=0.1.0; extra == "composio"
Requires-Dist: cryptography>=3.4.0; extra == "composio"
Provides-Extra: zstd
Requires-Dist: zstandard>=0.20.0; extra == "zstd"
Provides-Extra: dev
Requires-Dist: pytest>=7.0.0; extra == "dev"
Requires-Dist: pytest-asyncio>=0.21.0; extra == "dev"
Requires-Dist: pytest-cov>=4.0.0; extra == "dev"
Requires-Dist: pytest-benchmark>=4.0.0; extra == "dev"
Requires-Dist: black>=23.0.0; extra == "dev"
Requires-Dist: isort>=5.12.0; extra == "dev"
Requires-Dist: flake8>=6.0.0; extra == "dev"
Requires-Dist: mypy>=1.0.0; extra == "dev"
Requires-Dist: pre-commit>=3.0.0; extra == "dev"
Provides-Extra: docs
Requires-Dist: sphinx>=6.0.0; extra == "docs"
Requires-Dist: sphinx-rtd-theme>=1.2.0; extra == "docs"
Requires-Dist: myst-parser>=1.0.0; extra == "docs"
Requires-Dist: sphinx-autodoc-typehints>=1.20.0; extra == "docs"
Provides-Extra: all
Requires-Dist: context-reference-store[adk,composio,langchain,langgraph,llamaindex,zstd]; extra == "all"
Provides-Extra: full
Requires-Dist: context-reference-store[all,dev,docs]; extra == "full"
Dynamic: license-file
